{
  "schemaVersion": 1,
  "fetchedAt": 1784077175305,
  "contentHash": "bd9314abefc8",
  "breaking": [
    {
      "title": "Trump threatens to hit Iran power plants next week if no deal",
      "summary": "Asked how long the US strikes would carry on, the U.S President replied: \"They'll continue until I say it's enough.\"",
      "source": "The Hindu",
      "sourceGroup": "the_hindu",
      "url": "https://www.thehindu.com/news/international/trump-threatens-to-hit-iran-power-plants-next-week-if-no-deal/article71223840.ece",
      "publishedAt": 1784073981000,
      "category": "topStories",
      "region": "in",
      "language": "en",
      "id": "8261abae2d043121",
      "suppressionReason": null,
      "isBreaking": true,
      "breakingScore": 4.426,
      "breakingReasons": [
        "multi_source_velocity",
        "severity_lexicon"
      ],
      "sourceCount": 2,
      "allSources": [
        "ndtv",
        "the_hindu"
      ],
      "firstSeen": 1784073233000
    },
    {
      "title": "France vs Spain, World Cup semifinal: Oyarzabal, Porro score as Spain nullifies French attack to reach final",
      "summary": "France managed only two shots on target as Spain, chasing a second World Cup title, suffocated them",
      "source": "The Hindu",
      "sourceGroup": "the_hindu",
      "url": "https://www.thehindu.com/sport/football/france-vs-spain-fifa-world-cup-semifinal-match-report-oyarzabal-porro-goals-july-14-2026/article71223010.ece",
      "publishedAt": 1784066698000,
      "category": "topStories",
      "region": "in",
      "language": "en",
      "id": "61d641d62c1832a7",
      "suppressionReason": null,
      "isBreaking": true,
      "breakingScore": 4.257,
      "breakingReasons": [
        "multi_source_velocity",
        "severity_lexicon"
      ],
      "sourceCount": 2,
      "allSources": [
        "bbc",
        "the_hindu"
      ],
      "firstSeen": 1784064779000
    },
    {
      "title": "Seven Britons among those killed in Spain wildfires",
      "summary": "Twelve of the 13 victims were foreign nationals, Spanish authorities said on Tuesday.",
      "source": "BBC",
      "sourceGroup": "bbc",
      "url": "https://www.bbc.co.uk/news/articles/cp8l87784ngo?at_medium=RSS&at_campaign=rss",
      "publishedAt": 1784072037000,
      "category": "world",
      "region": "in",
      "language": "en",
      "id": "47a4dcda673c6b1c",
      "suppressionReason": null,
      "isBreaking": true,
      "breakingScore": 3.881,
      "breakingReasons": [
        "severity_lexicon"
      ],
      "sourceCount": 1,
      "allSources": [
        "bbc"
      ],
      "firstSeen": 1784072037000
    },
    {
      "title": "Trump withdraws planned 20% levy on Hormuz ships; attacks intensify",
      "summary": "The U.S. carried out another wave of strikes ahead of its planned reimposition of a blockade on Iran’s ports",
      "source": "The Hindu",
      "sourceGroup": "the_hindu",
      "url": "https://www.thehindu.com/news/international/trump-withdraws-planned-20-levy-on-hormuz-ships-calls-for-trade-deals-with-gulf-countries-instead/article71222372.ece",
      "publishedAt": 1784072021000,
      "category": "topStories",
      "region": "in",
      "language": "en",
      "id": "241843248980e9dc",
      "suppressionReason": null,
      "isBreaking": true,
      "breakingScore": 3.881,
      "breakingReasons": [
        "severity_lexicon"
      ],
      "sourceCount": 1,
      "allSources": [
        "the_hindu"
      ],
      "firstSeen": 1784072021000
    },
    {
      "title": "Venezuela Earthquake: Death Count Rises To 4,734, More Than 16,700 Injured",
      "summary": "The 7.2 and 7.5 magnitude quakes struck within a minute of each other on June 24.",
      "source": "NDTV",
      "sourceGroup": "ndtv",
      "url": "https://www.ndtv.com/world-news/venezuela-earthquake-death-count-rises-to-4-734-more-than-16-700-injured-11772478#publisher=newsstand",
      "publishedAt": 1784070256000,
      "category": "topStories",
      "region": "in",
      "language": "en",
      "id": "10fd46d9414e5c9e",
      "suppressionReason": null,
      "isBreaking": true,
      "breakingScore": 3.84,
      "breakingReasons": [
        "severity_lexicon"
      ],
      "sourceCount": 1,
      "allSources": [
        "ndtv"
      ],
      "firstSeen": 1784070256000
    },
    {
      "title": "US Halts Immigration Traffic Stops After 2 Fatal Shootings",
      "summary": "Last week, an ICE agent shot dead Lorenzo Salgado, a 52-year-old Mexican, during an operation in Texas.",
      "source": "NDTV",
      "sourceGroup": "ndtv",
      "url": "https://www.ndtv.com/world-news/us-halts-immigration-traffic-stops-after-2-fatal-shootings-11772182#publisher=newsstand",
      "publishedAt": 1784056896000,
      "category": "topStories",
      "region": "in",
      "language": "en",
      "id": "d3b085e9a5cd7c07",
      "suppressionReason": null,
      "isBreaking": true,
      "breakingScore": 3.531,
      "breakingReasons": [
        "severity_lexicon"
      ],
      "sourceCount": 1,
      "allSources": [
        "ndtv"
      ],
      "firstSeen": 1784056896000
    },
    {
      "title": "Midnight social media curfew proposed for older UK teens",
      "summary": "Teens will be able to opt out of the restrictions - campaigners have criticised them as being piecemeal.",
      "source": "BBC",
      "sourceGroup": "bbc",
      "url": "https://www.bbc.co.uk/news/articles/c982857nlrlo?at_medium=RSS&at_campaign=rss",
      "publishedAt": 1784071043000,
      "category": "world",
      "region": "in",
      "language": "en",
      "id": "0ff502daca04bc7e",
      "suppressionReason": null,
      "isBreaking": true,
      "breakingScore": 2.858,
      "breakingReasons": [
        "multi_source_velocity"
      ],
      "sourceCount": 2,
      "allSources": [
        "bbc",
        "ndtv"
      ],
      "firstSeen": 1784065857000
    },
    {
      "title": "Supreme Court says call records alone not cogent proof, clears woman of husband’s murder",
      "summary": "Mere production of telephone records does not substitute substantive proof of an illicit affair leading to murder, the top court said in the case dating back to 2007",
      "source": "The Hindu",
      "sourceGroup": "the_hindu",
      "url": "https://www.thehindu.com/news/national/sc-says-call-records-alone-not-cogent-proof-clears-woman-of-husbands-murder/article71221039.ece",
      "publishedAt": 1784057545000,
      "category": "topStories",
      "region": "in",
      "language": "en",
      "id": "332a62c55073f68e",
      "suppressionReason": null,
      "isBreaking": true,
      "breakingScore": 2.546,
      "breakingReasons": [
        "multi_source_velocity"
      ],
      "sourceCount": 2,
      "allSources": [
        "ndtv",
        "the_hindu"
      ],
      "firstSeen": 1784053074000
    }
  ]
}