{
  "checks": [
    {
      "ageHours": 0.01,
      "ageMs": 19101,
      "contentHash": "db05815ed9a4819a",
      "errors": [],
      "fetchedAt": 1783429284419,
      "name": "insight",
      "path": "public/newsdata/insight_latest.json",
      "status": "PASS",
      "storyCount": 611,
      "warnings": []
    },
    {
      "ageHours": 0.0,
      "ageMs": 10116,
      "contentHash": "4c64d3c6331a",
      "errors": [],
      "fetchedAt": 1783429293404,
      "name": "sections",
      "path": "public/newsdata/sections_latest.json",
      "status": "PASS",
      "storyCount": 288,
      "warnings": []
    }
  ],
  "errors": [],
  "generatedAt": 1783429303520,
  "schemaVersion": 1,
  "status": "PASS",
  "thresholds": {
    "maxAgeHours": 6.0,
    "maxFutureSkewMinutes": 10.0
  },
  "warnings": []
}