{
  "checks": [
    {
      "ageHours": 0.01,
      "ageMs": 30785,
      "contentHash": "029a5b75baa76da0",
      "errors": [],
      "fetchedAt": 1783919006192,
      "name": "insight",
      "path": "public/newsdata/insight_latest.json",
      "status": "PASS",
      "storyCount": 511,
      "warnings": []
    },
    {
      "ageHours": 0.0,
      "ageMs": 12847,
      "contentHash": "4edbd637b19c",
      "errors": [],
      "fetchedAt": 1783919024130,
      "name": "sections",
      "path": "public/newsdata/sections_latest.json",
      "status": "PASS",
      "storyCount": 275,
      "warnings": []
    }
  ],
  "errors": [],
  "generatedAt": 1783919036977,
  "schemaVersion": 1,
  "status": "PASS",
  "thresholds": {
    "maxAgeHours": 6.0,
    "maxFutureSkewMinutes": 10.0
  },
  "warnings": []
}