{
  "schemaVersion": "2.0.0",
  "generatedAt": "2026-07-05T10:21:13.131598Z",
  "generated_at": "2026-07-05T10:21:13.131602Z",
  "fetchedAt": 1783246873131,
  "sourceMode": "snapshot-worker-v2",
  "indices": [
    {
      "name": "NIFTY 50",
      "symbol": "^NSEI",
      "value": "24,270.85",
      "change": "95.15",
      "changePercent": "0.39",
      "direction": "up",
      "currency": "₹",
      "sourceMode": "yahoo-yfinance"
    },
    {
      "name": "SENSEX",
      "symbol": "^BSESN",
      "value": "77,763.91",
      "change": "261.79",
      "changePercent": "0.34",
      "direction": "up",
      "currency": "₹",
      "sourceMode": "yahoo-yfinance"
    },
    {
      "name": "NIFTY BANK",
      "symbol": "^NSEBANK",
      "value": "57,938.50",
      "change": "-93.15",
      "changePercent": "-0.16",
      "direction": "down",
      "currency": "₹",
      "sourceMode": "yahoo-yfinance"
    },
    {
      "name": "NIFTY IT",
      "symbol": "^CNXIT",
      "value": "27,439.40",
      "change": "474.35",
      "changePercent": "1.76",
      "direction": "up",
      "currency": "₹",
      "sourceMode": "yahoo-yfinance"
    },
    {
      "name": "NIFTY AUTO",
      "symbol": "^CNXAUTO",
      "value": "26,988.10",
      "change": "-120.10",
      "changePercent": "-0.44",
      "direction": "down",
      "currency": "₹",
      "sourceMode": "yahoo-yfinance"
    },
    {
      "name": "NIFTY PHARMA",
      "symbol": "^CNXPHARMA",
      "value": "25,745.15",
      "change": "436.25",
      "changePercent": "1.72",
      "direction": "up",
      "currency": "₹",
      "sourceMode": "yahoo-yfinance"
    }
  ],
  "globalIndices": [
    {
      "name": "S&P 500",
      "symbol": "^GSPC",
      "value": "7,483.24",
      "change": "0.01",
      "changePercent": "0.00",
      "direction": "up",
      "sourceMode": "yahoo-yfinance"
    },
    {
      "name": "HANG SENG",
      "symbol": "^HSI",
      "value": "23,350.03",
      "change": "295.00",
      "changePercent": "1.28",
      "direction": "up",
      "sourceMode": "yahoo-yfinance"
    },
    {
      "name": "NIKKEI 225",
      "symbol": "^N225",
      "value": "69,744.07",
      "change": "1010.92",
      "changePercent": "1.47",
      "direction": "up",
      "sourceMode": "yahoo-yfinance"
    },
    {
      "name": "DOW JONES",
      "symbol": "^DJI",
      "value": "52,900.07",
      "change": "594.83",
      "changePercent": "1.14",
      "direction": "up",
      "sourceMode": "yahoo-yfinance"
    },
    {
      "name": "NASDAQ",
      "symbol": "^IXIC",
      "value": "25,832.67",
      "change": "-207.36",
      "changePercent": "-0.80",
      "direction": "down",
      "sourceMode": "yahoo-yfinance"
    }
  ],
  "movers": {
    "gainers": [
      {
        "symbol": "BHARTIARTL",
        "price": "1910.40",
        "change": "35.40",
        "changePercent": "1.89",
        "direction": "up",
        "sourceMode": "yahoo-yfinance"
      },
      {
        "symbol": "SUNPHARMA",
        "price": "1904.80",
        "change": "33.80",
        "changePercent": "1.81",
        "direction": "up",
        "sourceMode": "yahoo-yfinance"
      },
      {
        "symbol": "BAJFINANCE",
        "price": "1031.40",
        "change": "13.00",
        "changePercent": "1.28",
        "direction": "up",
        "sourceMode": "yahoo-yfinance"
      },
      {
        "symbol": "WIPRO",
        "price": "176.08",
        "change": "2.08",
        "changePercent": "1.20",
        "direction": "up",
        "sourceMode": "yahoo-yfinance"
      },
      {
        "symbol": "ICICIBANK",
        "price": "1411.40",
        "change": "11.40",
        "changePercent": "0.81",
        "direction": "up",
        "sourceMode": "yahoo-yfinance"
      }
    ],
    "losers": [
      {
        "symbol": "AXISBANK",
        "price": "1342.10",
        "change": "-20.50",
        "changePercent": "-1.50",
        "direction": "down",
        "sourceMode": "yahoo-yfinance"
      },
      {
        "symbol": "SBIN",
        "price": "1040.00",
        "change": "-11.60",
        "changePercent": "-1.10",
        "direction": "down",
        "sourceMode": "yahoo-yfinance"
      },
      {
        "symbol": "LT",
        "price": "4026.60",
        "change": "-32.80",
        "changePercent": "-0.81",
        "direction": "down",
        "sourceMode": "yahoo-yfinance"
      },
      {
        "symbol": "KOTAKBANK",
        "price": "396.75",
        "change": "-2.55",
        "changePercent": "-0.64",
        "direction": "down",
        "sourceMode": "yahoo-yfinance"
      },
      {
        "symbol": "HINDUNILVR",
        "price": "2201.20",
        "change": "-9.40",
        "changePercent": "-0.43",
        "direction": "down",
        "sourceMode": "yahoo-yfinance"
      }
    ],
    "source": "yahoo-yfinance"
  },
  "sectorals": [
    {
      "name": "NIFTY BANK",
      "symbol": "^NSEBANK",
      "value": "57,938.50",
      "change": "-93.15",
      "changePercent": "-0.16",
      "direction": "down",
      "currency": "₹",
      "sourceMode": "yahoo-yfinance"
    },
    {
      "name": "NIFTY IT",
      "symbol": "^CNXIT",
      "value": "27,439.40",
      "change": "474.35",
      "changePercent": "1.76",
      "direction": "up",
      "currency": "₹",
      "sourceMode": "yahoo-yfinance"
    },
    {
      "name": "NIFTY AUTO",
      "symbol": "^CNXAUTO",
      "value": "26,988.10",
      "change": "-120.10",
      "changePercent": "-0.44",
      "direction": "down",
      "currency": "₹",
      "sourceMode": "yahoo-yfinance"
    },
    {
      "name": "NIFTY PHARMA",
      "symbol": "^CNXPHARMA",
      "value": "25,745.15",
      "change": "436.25",
      "changePercent": "1.72",
      "direction": "up",
      "currency": "₹",
      "sourceMode": "yahoo-yfinance"
    }
  ],
  "commodities": [
    {
      "name": "Silver",
      "symbol": "SI=F",
      "value": "$62.81",
      "unit": "$/oz",
      "change": "2.17",
      "changePercent": "3.58",
      "direction": "up",
      "source": "yahoo-yfinance"
    },
    {
      "name": "Gold",
      "symbol": "GC=F",
      "value": "$4187.30",
      "unit": "$/oz",
      "change": "74.60",
      "changePercent": "1.81",
      "direction": "up",
      "source": "yahoo-yfinance"
    },
    {
      "name": "Crude Oil",
      "symbol": "CL=F",
      "value": "$68.78",
      "unit": "$/bbl",
      "change": "0.09",
      "changePercent": "0.13",
      "direction": "up",
      "source": "yahoo-yfinance"
    }
  ],
  "currencies": [
    {
      "name": "GBP/INR",
      "pair": "GBPINR",
      "symbol": "GBPINR=X",
      "value": "₹127.0716",
      "rate": 127.07160186767578,
      "change": "0.7545",
      "changePercent": "0.60",
      "direction": "up",
      "source": "yahoo-yfinance",
      "mode": "fallback-intraday",
      "asOf": "2026-07-05T10:19:30.329254Z"
    },
    {
      "name": "JPY/INR",
      "pair": "JPYINR",
      "symbol": "JPYINR=X",
      "value": "₹0.5899",
      "rate": 0.5898500084877014,
      "change": "0.0043",
      "changePercent": "0.73",
      "direction": "up",
      "source": "yahoo-yfinance",
      "mode": "fallback-intraday",
      "asOf": "2026-07-05T10:19:30.369161Z"
    },
    {
      "name": "OMR/INR",
      "pair": "OMRINR",
      "symbol": "OMRINR=X",
      "value": "₹246.8400",
      "rate": 246.83999633789062,
      "change": "0.0000",
      "changePercent": "0.00",
      "direction": "up",
      "source": "yahoo-yfinance",
      "mode": "fallback-intraday",
      "asOf": "2026-07-05T10:19:30.381222Z"
    },
    {
      "name": "USD/INR",
      "pair": "USDINR",
      "symbol": "USDINR=X",
      "value": "₹95.2000",
      "rate": 95.19999694824219,
      "change": "-0.2175",
      "changePercent": "-0.23",
      "direction": "down",
      "source": "yahoo-yfinance",
      "mode": "fallback-intraday",
      "asOf": "2026-07-05T10:19:30.393483Z"
    },
    {
      "name": "EUR/INR",
      "pair": "EURINR",
      "symbol": "EURINR=X",
      "value": "₹108.8990",
      "rate": 108.89900207519531,
      "change": "0.6010",
      "changePercent": "0.55",
      "direction": "up",
      "source": "yahoo-yfinance",
      "mode": "fallback-intraday",
      "asOf": "2026-07-05T10:19:30.463356Z"
    }
  ],
  "mutualFunds": [
    {
      "instrumentType": "mutualFund",
      "schemeCode": "120348",
      "isinGrowth": "INF205K01LE4",
      "isinDividendReinvestment": "-",
      "name": "Invesco India Contra Fund - Direct Plan - Growth",
      "nav": 158.13,
      "navDate": "03-Jul-2026",
      "source": {
        "provider": "amfi_navall",
        "mode": "official-daily",
        "fetchedAt": "2026-07-05T10:19:33.063537Z"
      },
      "extras": {},
      "fundType": "value",
      "fundHouse": "Invesco Mutual Fund",
      "category": "value"
    },
    {
      "instrumentType": "mutualFund",
      "schemeCode": "119769",
      "isinGrowth": "INF174K01KZ9",
      "isinDividendReinvestment": "-",
      "name": "Kotak Contra Fund - Direct Plan - Growth",
      "nav": 183.502,
      "navDate": "03-Jul-2026",
      "source": {
        "provider": "amfi_navall",
        "mode": "official-daily",
        "fetchedAt": "2026-07-05T10:19:33.063558Z"
      },
      "extras": {},
      "fundType": "value",
      "fundHouse": "Kotak Mahindra Mutual Fund",
      "category": "value"
    },
    {
      "instrumentType": "mutualFund",
      "schemeCode": "154337",
      "isinGrowth": "INF247L01GW6",
      "isinDividendReinvestment": "-",
      "name": "Motilal Oswal Contra Fund - Direct â Growth",
      "nav": 10.5243,
      "navDate": "03-Jul-2026",
      "source": {
        "provider": "amfi_navall",
        "mode": "official-daily",
        "fetchedAt": "2026-07-05T10:19:33.063580Z"
      },
      "extras": {},
      "fundType": "value",
      "fundHouse": "Motilal Oswal Mutual Fund",
      "category": "value"
    },
    {
      "instrumentType": "mutualFund",
      "schemeCode": "119835",
      "isinGrowth": "INF200K01RA0",
      "isinDividendReinvestment": "-",
      "name": "SBI CONTRA FUND - DIRECT PLAN - GROWTH",
      "nav": 413.6646,
      "navDate": "03-Jul-2026",
      "source": {
        "provider": "amfi_navall",
        "mode": "official-daily",
        "fetchedAt": "2026-07-05T10:19:33.063599Z"
      },
      "extras": {},
      "fundType": "value",
      "fundHouse": "SBI Mutual Fund",
      "category": "value"
    },
    {
      "instrumentType": "mutualFund",
      "schemeCode": "151165",
      "isinGrowth": "INF579M01AN2",
      "isinDividendReinvestment": "-",
      "name": "360 ONE ELSS Tax Saver Nifty 50 Index Fund - Direct Plan - Growth",
      "nav": 13.7781,
      "navDate": "03-Jul-2026",
      "source": {
        "provider": "amfi_navall",
        "mode": "official-daily",
        "fetchedAt": "2026-07-05T10:19:33.063875Z"
      },
      "extras": {},
      "fundType": "elss",
      "fundHouse": "360 ONE Mutual Fund",
      "category": "elss"
    },
    {
      "instrumentType": "mutualFund",
      "schemeCode": "119544",
      "isinGrowth": "INF209K01UN8",
      "isinDividendReinvestment": "-",
      "name": "Aditya Birla Sun Life ELSS Tax Saver Fund - Growth - Direct Plan",
      "nav": 69.56,
      "navDate": "03-Jul-2026",
      "source": {
        "provider": "amfi_navall",
        "mode": "official-daily",
        "fetchedAt": "2026-07-05T10:19:33.063896Z"
      },
      "extras": {},
      "fundType": "elss",
      "fundHouse": "Aditya Birla Sun Life Mutual Fund",
      "category": "elss"
    },
    {
      "instrumentType": "mutualFund",
      "schemeCode": "120503",
      "isinGrowth": "INF846K01EW2",
      "isinDividendReinvestment": "-",
      "name": "Axis ELSS Tax Saver Fund - Direct Plan - Growth Option",
      "nav": 109.3672,
      "navDate": "03-Jul-2026",
      "source": {
        "provider": "amfi_navall",
        "mode": "official-daily",
        "fetchedAt": "2026-07-05T10:19:33.063917Z"
      },
      "extras": {},
      "fundType": "elss",
      "fundHouse": "Axis Mutual Fund",
      "category": "elss"
    },
    {
      "instrumentType": "mutualFund",
      "schemeCode": "153201",
      "isinGrowth": "INF0QA701AK0",
      "isinDividendReinvestment": "-",
      "name": "BAJAJ FINSERV ELSS TAX SAVER FUND - DIRECT - GROWTH",
      "nav": 11.931,
      "navDate": "03-Jul-2026",
      "source": {
        "provider": "amfi_navall",
        "mode": "official-daily",
        "fetchedAt": "2026-07-05T10:19:33.063939Z"
      },
      "extras": {},
      "fundType": "elss",
      "fundHouse": "Bajaj Finserv Mutual Fund",
      "category": "elss"
    },
    {
      "instrumentType": "mutualFund",
      "schemeCode": "118473",
      "isinGrowth": "INF194K01Y29",
      "isinDividendReinvestment": "-",
      "name": "BANDHAN ELSS Tax Saver Fund - Direct Plan - Growth",
      "nav": 179.987,
      "navDate": "03-Jul-2026",
      "source": {
        "provider": "amfi_navall",
        "mode": "official-daily",
        "fetchedAt": "2026-07-05T10:19:33.063957Z"
      },
      "extras": {},
      "fundType": "elss",
      "fundHouse": "Bandhan Mutual Fund",
      "category": "elss"
    },
    {
      "instrumentType": "mutualFund",
      "schemeCode": "119351",
      "isinGrowth": "INF761K01884",
      "isinDividendReinvestment": "-",
      "name": "BANK OF INDIA ELSS Tax Saver -Direct Plan- Growth",
      "nav": 194.55,
      "navDate": "03-Jul-2026",
      "source": {
        "provider": "amfi_navall",
        "mode": "official-daily",
        "fetchedAt": "2026-07-05T10:19:33.063980Z"
      },
      "extras": {},
      "fundType": "elss",
      "fundHouse": "Bank of India Mutual Fund",
      "category": "elss"
    },
    {
      "instrumentType": "mutualFund",
      "schemeCode": "150159",
      "isinGrowth": "INF251K01HF3",
      "isinDividendReinvestment": "-",
      "name": "BARODA BNP PARIBAS ELSS Tax Saver Fund - Direct Plan - Growth Option",
      "nav": 112.12,
      "navDate": "03-Jul-2026",
      "source": {
        "provider": "amfi_navall",
        "mode": "official-daily",
        "fetchedAt": "2026-07-05T10:19:33.064009Z"
      },
      "extras": {},
      "fundType": "elss",
      "fundHouse": "Baroda BNP Paribas Mutual Fund",
      "category": "elss"
    },
    {
      "instrumentType": "mutualFund",
      "schemeCode": "118285",
      "isinGrowth": "INF760K01EL8",
      "isinDividendReinvestment": "-",
      "name": "CANARA ROBECO ELSS TAX SAVER - DIRECT PLAN - GROWTH OPTION",
      "nav": 201.85,
      "navDate": "03-Jul-2026",
      "source": {
        "provider": "amfi_navall",
        "mode": "official-daily",
        "fetchedAt": "2026-07-05T10:19:33.064030Z"
      },
      "extras": {},
      "fundType": "elss",
      "fundHouse": "Canara Robeco Mutual Fund",
      "category": "elss"
    },
    {
      "instrumentType": "mutualFund",
      "schemeCode": "119242",
      "isinGrowth": "INF740K01OK1",
      "isinDividendReinvestment": "-",
      "name": "DSP ELSS Tax Saver Fund - Direct Plan - Growth",
      "nav": 156.717,
      "navDate": "03-Jul-2026",
      "source": {
        "provider": "amfi_navall",
        "mode": "official-daily",
        "fetchedAt": "2026-07-05T10:19:33.064048Z"
      },
      "extras": {},
      "fundType": "elss",
      "fundHouse": "DSP Mutual Fund",
      "category": "elss"
    },
    {
      "instrumentType": "mutualFund",
      "schemeCode": "118620",
      "isinGrowth": "INF754K01CA8",
      "isinDividendReinvestment": "-",
      "name": "Edelweiss ELSS Tax Saver Fund - Direct Plan-Growth Option",
      "nav": 137.53,
      "navDate": "03-Jul-2026",
      "source": {
        "provider": "amfi_navall",
        "mode": "official-daily",
        "fetchedAt": "2026-07-05T10:19:33.064076Z"
      },
      "extras": {},
      "fundType": "elss",
      "fundHouse": "Edelweiss Mutual Fund",
      "category": "elss"
    },
    {
      "instrumentType": "mutualFund",
      "schemeCode": "118540",
      "isinGrowth": "INF090I01JS8",
      "isinDividendReinvestment": "-",
      "name": "Franklin India ELSS Tax Saver Fund - Direct - Growth",
      "nav": 1605.9173,
      "navDate": "03-Jul-2026",
      "source": {
        "provider": "amfi_navall",
        "mode": "official-daily",
        "fetchedAt": "2026-07-05T10:19:33.064090Z"
      },
      "extras": {},
      "fundType": "elss",
      "fundHouse": "Franklin Templeton Mutual Fund",
      "category": "elss"
    },
    {
      "instrumentType": "mutualFund",
      "schemeCode": "141808",
      "isinGrowth": "INF666M01DK7",
      "isinDividendReinvestment": "-",
      "name": "Groww ELSS Tax Saver Fund (formerly known as Indiabulls Tax Savings Fund)- Direct Plan- Growth Option",
      "nav": 21.87,
      "navDate": "03-Jul-2026",
      "source": {
        "provider": "amfi_navall",
        "mode": "official-daily",
        "fetchedAt": "2026-07-05T10:19:33.064116Z"
      },
      "extras": {},
      "fundType": "elss",
      "fundHouse": "Groww Mutual Fund",
      "category": "elss"
    },
    {
      "instrumentType": "mutualFund",
      "schemeCode": "119060",
      "isinGrowth": "INF179K01YS4",
      "isinDividendReinvestment": "-",
      "name": "HDFC ELSS Tax saver - Growth Option - Direct Plan",
      "nav": 1491.433,
      "navDate": "03-Jul-2026",
      "source": {
        "provider": "amfi_navall",
        "mode": "official-daily",
        "fetchedAt": "2026-07-05T10:19:33.064135Z"
      },
      "extras": {},
      "fundType": "elss",
      "fundHouse": "HDFC Mutual Fund",
      "category": "elss"
    },
    {
      "instrumentType": "mutualFund",
      "schemeCode": "151078",
      "isinGrowth": "INF917K01GP0",
      "isinDividendReinvestment": "-",
      "name": "HSBC ELSS Tax saver Fund - Direct Growth",
      "nav": 153.1178,
      "navDate": "03-Jul-2026",
      "source": {
        "provider": "amfi_navall",
        "mode": "official-daily",
        "fetchedAt": "2026-07-05T10:19:33.064170Z"
      },
      "extras": {},
      "fundType": "elss",
      "fundHouse": "HSBC Mutual Fund",
      "category": "elss"
    },
    {
      "instrumentType": "mutualFund",
      "schemeCode": "120592",
      "isinGrowth": "INF109K01Y31",
      "isinDividendReinvestment": "-",
      "name": "ICICI Prudential ELSS Tax Saver Fund - Direct Plan - Growth",
      "nav": 1045.55,
      "navDate": "03-Jul-2026",
      "source": {
        "provider": "amfi_navall",
        "mode": "official-daily",
        "fetchedAt": "2026-07-05T10:19:33.064194Z"
      },
      "extras": {},
      "fundType": "elss",
      "fundHouse": "ICICI Prudential Mutual Fund",
      "category": "elss"
    },
    {
      "instrumentType": "mutualFund",
      "schemeCode": "120416",
      "isinGrowth": "INF205K01NT8",
      "isinDividendReinvestment": "-",
      "name": "Invesco India ELSS Tax Saver Fund - Direct Plan - Growth",
      "nav": 147.87,
      "navDate": "03-Jul-2026",
      "source": {
        "provider": "amfi_navall",
        "mode": "official-daily",
        "fetchedAt": "2026-07-05T10:19:33.064212Z"
      },
      "extras": {},
      "fundType": "elss",
      "fundHouse": "Invesco Mutual Fund",
      "category": "elss"
    },
    {
      "instrumentType": "mutualFund",
      "schemeCode": "147541",
      "isinGrowth": "INF00XX01390",
      "isinDividendReinvestment": "-",
      "name": "ITI ELSS Tax Saver Fund - Direct Plan - Growth Option",
      "nav": 28.9473,
      "navDate": "03-Jul-2026",
      "source": {
        "provider": "amfi_navall",
        "mode": "official-daily",
        "fetchedAt": "2026-07-05T10:19:33.064234Z"
      },
      "extras": {},
      "fundType": "elss",
      "fundHouse": "ITI Mutual Fund",
      "category": "elss"
    },
    {
      "instrumentType": "mutualFund",
      "schemeCode": "120494",
      "isinGrowth": "INF192K01CE3",
      "isinDividendReinvestment": "-",
      "name": "JM ELSS Tax Saver Fund (Direct) - Growth Option",
      "nav": 58.4279,
      "navDate": "03-Jul-2026",
      "source": {
        "provider": "amfi_navall",
        "mode": "official-daily",
        "fetchedAt": "2026-07-05T10:19:33.064253Z"
      },
      "extras": {},
      "fundType": "elss",
      "fundHouse": "JM Financial Mutual Fund",
      "category": "elss"
    },
    {
      "instrumentType": "mutualFund",
      "schemeCode": "119773",
      "isinGrowth": "INF174K01LI3",
      "isinDividendReinvestment": "-",
      "name": "Kotak ELSS Tax Saver Fund-Growth - Direct",
      "nav": 137.561,
      "navDate": "03-Jul-2026",
      "source": {
        "provider": "amfi_navall",
        "mode": "official-daily",
        "fetchedAt": "2026-07-05T10:19:33.064275Z"
      },
      "extras": {},
      "fundType": "elss",
      "fundHouse": "Kotak Mahindra Mutual Fund",
      "category": "elss"
    },
    {
      "instrumentType": "mutualFund",
      "schemeCode": "120270",
      "isinGrowth": "INF767K01EM1",
      "isinDividendReinvestment": "-",
      "name": "LIC MF ELSS Tax Saver-Direct Plan-Growth",
      "nav": 170.2722,
      "navDate": "03-Jul-2026",
      "source": {
        "provider": "amfi_navall",
        "mode": "official-daily",
        "fetchedAt": "2026-07-05T10:19:33.064294Z"
      },
      "extras": {},
      "fundType": "elss",
      "fundHouse": "LIC Mutual Fund",
      "category": "elss"
    },
    {
      "instrumentType": "mutualFund",
      "schemeCode": "139781",
      "isinGrowth": "INF174V01093",
      "isinDividendReinvestment": "-",
      "name": "Mahindra Manulife ELSS Tax Saver Fund - Direct Plan -Growth",
      "nav": 32.6835,
      "navDate": "03-Jul-2026",
      "source": {
        "provider": "amfi_navall",
        "mode": "official-daily",
        "fetchedAt": "2026-07-05T10:19:33.064493Z"
      },
      "extras": {},
      "fundType": "elss",
      "fundHouse": "Mahindra Manulife Mutual Fund",
      "category": "elss"
    },
    {
      "instrumentType": "mutualFund",
      "schemeCode": "135781",
      "isinGrowth": "INF769K01DM9",
      "isinDividendReinvestment": "-",
      "name": "Mirae Asset ELSS Tax Saver Fund - Direct Plan - Growth",
      "nav": 57.847,
      "navDate": "03-Jul-2026",
      "source": {
        "provider": "amfi_navall",
        "mode": "official-daily",
        "fetchedAt": "2026-07-05T10:19:33.064511Z"
      },
      "extras": {},
      "fundType": "elss",
      "fundHouse": "Mirae Asset Mutual Fund",
      "category": "elss"
    },
    {
      "instrumentType": "mutualFund",
      "schemeCode": "133386",
      "isinGrowth": "INF247L01569",
      "isinDividendReinvestment": "-",
      "name": "Motilal Oswal ELSS Tax Saver Fund - Direct Plan - Growth Option",
      "nav": 64.469,
      "navDate": "03-Jul-2026",
      "source": {
        "provider": "amfi_navall",
        "mode": "official-daily",
        "fetchedAt": "2026-07-05T10:19:33.064531Z"
      },
      "extras": {},
      "fundType": "elss",
      "fundHouse": "Motilal Oswal Mutual Fund",
      "category": "elss"
    },
    {
      "instrumentType": "mutualFund",
      "schemeCode": "135654",
      "isinGrowth": "INF959L01CD5",
      "isinDividendReinvestment": "-",
      "name": "Navi ELSS Tax Saver Fund- Direct Plan- Growth Option",
      "nav": 32.8119,
      "navDate": "10-Apr-2026",
      "source": {
        "provider": "amfi_navall",
        "mode": "official-daily",
        "fetchedAt": "2026-07-05T10:19:33.064559Z"
      },
      "extras": {},
      "fundType": "elss",
      "fundHouse": "Navi Mutual Fund",
      "category": "elss"
    },
    {
      "instrumentType": "mutualFund",
      "schemeCode": "151471",
      "isinGrowth": "INF959L01GR6",
      "isinDividendReinvestment": "-",
      "name": "NAVI ELSS TAX SAVER NIFTY 50 INDEX FUND - DIRECT PLAN GROWTH",
      "nav": 14.7379,
      "navDate": "03-Jul-2026",
      "source": {
        "provider": "amfi_navall",
        "mode": "official-daily",
        "fetchedAt": "2026-07-05T10:19:33.064568Z"
      },
      "extras": {},
      "fundType": "elss",
      "fundHouse": "Navi Mutual Fund",
      "category": "elss"
    },
    {
      "instrumentType": "mutualFund",
      "schemeCode": "118803",
      "isinGrowth": "INF204K01L55",
      "isinDividendReinvestment": "-",
      "name": "Nippon India ELSS Tax Saver Fund - Direct Plan Growth Plan - Growth Option",
      "nav": 145.3652,
      "navDate": "03-Jul-2026",
      "source": {
        "provider": "amfi_navall",
        "mode": "official-daily",
        "fetchedAt": "2026-07-05T10:19:33.064610Z"
      },
      "extras": {},
      "fundType": "elss",
      "fundHouse": "Nippon India Mutual Fund",
      "category": "elss"
    },
    {
      "instrumentType": "mutualFund",
      "schemeCode": "151611",
      "isinGrowth": "INF0J8L01115",
      "isinDividendReinvestment": "-",
      "name": "NJ ELSS Tax Saver Scheme Direct Growth",
      "nav": 14.75,
      "navDate": "03-Jul-2026",
      "source": {
        "provider": "amfi_navall",
        "mode": "official-daily",
        "fetchedAt": "2026-07-05T10:19:33.064624Z"
      },
      "extras": {},
      "fundType": "elss",
      "fundHouse": "NJ Mutual Fund",
      "category": "elss"
    },
    {
      "instrumentType": "mutualFund",
      "schemeCode": "135601",
      "isinGrowth": "INF663L01FN5",
      "isinDividendReinvestment": "-",
      "name": "PGIM India ELSS Tax Saver Fund - Direct Plan - Growth Option",
      "nav": 39.87,
      "navDate": "03-Jul-2026",
      "source": {
        "provider": "amfi_navall",
        "mode": "official-daily",
        "fetchedAt": "2026-07-05T10:19:33.064665Z"
      },
      "extras": {},
      "fundType": "elss",
      "fundHouse": "PGIM India Mutual Fund",
      "category": "elss"
    },
    {
      "instrumentType": "mutualFund",
      "schemeCode": "147481",
      "isinGrowth": "INF879O01100",
      "isinDividendReinvestment": "-",
      "name": "Parag Parikh ELSS Tax Saver Fund- Direct Growth",
      "nav": 32.2972,
      "navDate": "03-Jul-2026",
      "source": {
        "provider": "amfi_navall",
        "mode": "official-daily",
        "fetchedAt": "2026-07-05T10:19:33.064680Z"
      },
      "extras": {},
      "fundType": "elss",
      "fundHouse": "PPFAS Mutual Fund",
      "category": "elss"
    },
    {
      "instrumentType": "mutualFund",
      "schemeCode": "120847",
      "isinGrowth": "INF966L01986",
      "isinDividendReinvestment": "-",
      "name": "quant ELSS Tax Saver Fund - Growth Option - Direct Plan",
      "nav": 457.1134,
      "navDate": "03-Jul-2026",
      "source": {
        "provider": "amfi_navall",
        "mode": "official-daily",
        "fetchedAt": "2026-07-05T10:19:33.064690Z"
      },
      "extras": {},
      "fundType": "elss",
      "fundHouse": "quant Mutual Fund",
      "category": "elss"
    },
    {
      "instrumentType": "mutualFund",
      "schemeCode": "111549",
      "isinGrowth": "INF082J01069",
      "isinDividendReinvestment": "-",
      "name": "Quantum ELSS Tax Saver Fund - Direct Plan Growth Option",
      "nav": 125.5,
      "navDate": "03-Jul-2026",
      "source": {
        "provider": "amfi_navall",
        "mode": "official-daily",
        "fetchedAt": "2026-07-05T10:19:33.064710Z"
      },
      "extras": {},
      "fundType": "elss",
      "fundHouse": "Quantum Mutual Fund",
      "category": "elss"
    },
    {
      "instrumentType": "mutualFund",
      "schemeCode": "150838",
      "isinGrowth": "INF0K1H01065",
      "isinDividendReinvestment": "-",
      "name": "Samco ELSS Tax Saver Fund - Direct Plan - Growth Option",
      "nav": 13.25,
      "navDate": "03-Jul-2026",
      "source": {
        "provider": "amfi_navall",
        "mode": "official-daily",
        "fetchedAt": "2026-07-05T10:19:33.064730Z"
      },
      "extras": {},
      "fundType": "elss",
      "fundHouse": "Samco Mutual Fund",
      "category": "elss"
    },
    {
      "instrumentType": "mutualFund",
      "schemeCode": "119723",
      "isinGrowth": "INF200K01UM9",
      "isinDividendReinvestment": "-",
      "name": "SBI ELSS Tax Saver FUND - DIRECT PLAN -GROWTH",
      "nav": 476.9773,
      "navDate": "03-Jul-2026",
      "source": {
        "provider": "amfi_navall",
        "mode": "official-daily",
        "fetchedAt": "2026-07-05T10:19:33.064745Z"
      },
      "extras": {},
      "fundType": "elss",
      "fundHouse": "SBI Mutual Fund",
      "category": "elss"
    },
    {
      "instrumentType": "mutualFund",
      "schemeCode": "145819",
      "isinGrowth": "INF680P01158",
      "isinDividendReinvestment": "-",
      "name": "Shriram ELSS Tax Saver Fund - Direct Growth",
      "nav": 23.8202,
      "navDate": "03-Jul-2026",
      "source": {
        "provider": "amfi_navall",
        "mode": "official-daily",
        "fetchedAt": "2026-07-05T10:19:33.064759Z"
      },
      "extras": {},
      "fundType": "elss",
      "fundHouse": "Shriram Mutual Fund",
      "category": "elss"
    },
    {
      "instrumentType": "mutualFund",
      "schemeCode": "149570",
      "isinGrowth": "INF173K01HZ7",
      "isinDividendReinvestment": "-",
      "name": "Sundaram ELSS Tax Saver Fund Direct Plan Growth",
      "nav": 535.3518,
      "navDate": "03-Jul-2026",
      "source": {
        "provider": "amfi_navall",
        "mode": "official-daily",
        "fetchedAt": "2026-07-05T10:19:33.064783Z"
      },
      "extras": {},
      "fundType": "elss",
      "fundHouse": "Sundaram Mutual Fund",
      "category": "elss"
    },
    {
      "instrumentType": "mutualFund",
      "schemeCode": "132756",
      "isinGrowth": "INF277K01I86",
      "isinDividendReinvestment": "-",
      "name": "Tata ELSS Fund-Growth-Direct Plan",
      "nav": 53.6544,
      "navDate": "03-Jul-2026",
      "source": {
        "provider": "amfi_navall",
        "mode": "official-daily",
        "fetchedAt": "2026-07-05T10:19:33.064824Z"
      },
      "extras": {},
      "fundType": "elss",
      "fundHouse": "Tata Mutual Fund",
      "category": "elss"
    },
    {
      "instrumentType": "mutualFund",
      "schemeCode": "118866",
      "isinGrowth": "INF044D01CG6",
      "isinDividendReinvestment": "INF044D01AA3",
      "name": "Taurus ELSS Tax Saver Fund - Direct Plan - Growth",
      "nav": 196.24,
      "navDate": "03-Jul-2026",
      "source": {
        "provider": "amfi_navall",
        "mode": "official-daily",
        "fetchedAt": "2026-07-05T10:19:33.064835Z"
      },
      "extras": {},
      "fundType": "elss",
      "fundHouse": "Taurus Mutual Fund",
      "category": "elss"
    },
    {
      "instrumentType": "mutualFund",
      "schemeCode": "119307",
      "isinGrowth": "INF582M01765",
      "isinDividendReinvestment": "-",
      "name": "Union ELSS Tax Saver Fund - Direct Plan - Growth Option",
      "nav": 71.58,
      "navDate": "03-Jul-2026",
      "source": {
        "provider": "amfi_navall",
        "mode": "official-daily",
        "fetchedAt": "2026-07-05T10:19:33.064857Z"
      },
      "extras": {},
      "fundType": "elss",
      "fundHouse": "Union Mutual Fund",
      "category": "elss"
    },
    {
      "instrumentType": "mutualFund",
      "schemeCode": "120715",
      "isinGrowth": "INF789F01TF7",
      "isinDividendReinvestment": "-",
      "name": "UTI ELSS Tax Saver Fund - Direct Plan - Growth Option",
      "nav": 227.9765,
      "navDate": "03-Jul-2026",
      "source": {
        "provider": "amfi_navall",
        "mode": "official-daily",
        "fetchedAt": "2026-07-05T10:19:33.064875Z"
      },
      "extras": {},
      "fundType": "elss",
      "fundHouse": "UTI Mutual Fund",
      "category": "elss"
    },
    {
      "instrumentType": "mutualFund",
      "schemeCode": "150587",
      "isinGrowth": "INF03VN01621",
      "isinDividendReinvestment": "-",
      "name": "WhiteOak Capital ELSS Tax Saver Fund Direct Plan Growth",
      "nav": 18.849,
      "navDate": "03-Jul-2026",
      "source": {
        "provider": "amfi_navall",
        "mode": "official-daily",
        "fetchedAt": "2026-07-05T10:19:33.064895Z"
      },
      "extras": {},
      "fundType": "elss",
      "fundHouse": "WhiteOak Capital Mutual Fund",
      "category": "elss"
    },
    {
      "instrumentType": "mutualFund",
      "schemeCode": "154043",
      "isinGrowth": "INF2JJD01136",
      "isinDividendReinvestment": "-",
      "name": "Abakkus Flexi Cap Fund - Direct - Growth",
      "nav": 10.987,
      "navDate": "03-Jul-2026",
      "source": {
        "provider": "amfi_navall",
        "mode": "official-daily",
        "fetchedAt": "2026-07-05T10:19:33.064936Z"
      },
      "extras": {},
      "fundType": "flexi-cap",
      "fundHouse": "Abakkus Mutual Fund",
      "category": "flexi-cap"
    },
    {
      "instrumentType": "mutualFund",
      "schemeCode": "120564",
      "isinGrowth": "INF209K01XX1",
      "isinDividendReinvestment": "-",
      "name": "Aditya Birla Sun Life Flexi Cap Fund - Growth - Direct Plan",
      "nav": 2148.35,
      "navDate": "03-Jul-2026",
      "source": {
        "provider": "amfi_navall",
        "mode": "official-daily",
        "fetchedAt": "2026-07-05T10:19:33.064956Z"
      },
      "extras": {},
      "fundType": "flexi-cap",
      "fundHouse": "Aditya Birla Sun Life Mutual Fund",
      "category": "flexi-cap"
    },
    {
      "instrumentType": "mutualFund",
      "schemeCode": "141925",
      "isinGrowth": "INF846K01B28",
      "isinDividendReinvestment": "-",
      "name": "Axis Flexi Cap Fund - Direct Plan - Growth",
      "nav": 30.72,
      "navDate": "03-Jul-2026",
      "source": {
        "provider": "amfi_navall",
        "mode": "official-daily",
        "fetchedAt": "2026-07-05T10:19:33.064976Z"
      },
      "extras": {},
      "fundType": "flexi-cap",
      "fundHouse": "Axis Mutual Fund",
      "category": "flexi-cap"
    },
    {
      "instrumentType": "mutualFund",
      "schemeCode": "151895",
      "isinGrowth": "INF0QA701342",
      "isinDividendReinvestment": "-",
      "name": "Bajaj Finserv Flexi Cap Fund-Direct Plan-Growth",
      "nav": 16.104,
      "navDate": "03-Jul-2026",
      "source": {
        "provider": "amfi_navall",
        "mode": "official-daily",
        "fetchedAt": "2026-07-05T10:19:33.065002Z"
      },
      "extras": {},
      "fundType": "flexi-cap",
      "fundHouse": "Bajaj Finserv Mutual Fund",
      "category": "flexi-cap"
    },
    {
      "instrumentType": "mutualFund",
      "schemeCode": "118424",
      "isinGrowth": "INF194K01W62",
      "isinDividendReinvestment": "-",
      "name": "BANDHAN Flexi Cap Fund-Direct Plan-Growth",
      "nav": 232.356,
      "navDate": "03-Jul-2026",
      "source": {
        "provider": "amfi_navall",
        "mode": "official-daily",
        "fetchedAt": "2026-07-05T10:19:33.065026Z"
      },
      "extras": {},
      "fundType": "flexi-cap",
      "fundHouse": "Bandhan Mutual Fund",
      "category": "flexi-cap"
    },
    {
      "instrumentType": "mutualFund",
      "schemeCode": "148404",
      "isinGrowth": "INF761K01FF5",
      "isinDividendReinvestment": "-",
      "name": "BANK OF INDIA Flexi Cap Fund Direct Plan -Growth",
      "nav": 41.13,
      "navDate": "03-Jul-2026",
      "source": {
        "provider": "amfi_navall",
        "mode": "official-daily",
        "fetchedAt": "2026-07-05T10:19:33.065040Z"
      },
      "extras": {},
      "fundType": "flexi-cap",
      "fundHouse": "Bank of India Mutual Fund",
      "category": "flexi-cap"
    }
  ],
  "ipo": {
    "upcoming": [],
    "live": [],
    "recent": []
  },
  "nfo": [],
  "ipoLastCheckedAt": "2026-07-05T10:19:35.089340+00:00",
  "marketNews": [],
  "stockCategories": {
    "highs": [],
    "lows": [],
    "all": []
  },
  "fiidii": {
    "fii": {},
    "dii": {},
    "date": ""
  },
  "sourceHealth": {
    "indices": {
      "status": "ok",
      "provider": "yahoo_yfinance",
      "mode": "ok",
      "message": "6 Indian indices fetched"
    },
    "globalIndices": {
      "status": "ok",
      "provider": "yahoo_yfinance",
      "mode": "ok",
      "message": "5 global indices fetched"
    },
    "movers": {
      "status": "ok",
      "provider": "yahoo_yfinance",
      "mode": "ok",
      "message": "15 stocks scanned for movers"
    },
    "commodities": {
      "status": "ok",
      "provider": "yahoo_yfinance",
      "mode": "ok",
      "message": "3 commodity rows fetched"
    },
    "fx": {
      "status": "ok",
      "provider": "yahoo_yfinance",
      "mode": "ok",
      "message": "RBI reference scrape failed: unknown; 5 FX pairs fetched from Yahoo fallback"
    },
    "mutualFunds": {
      "status": "ok",
      "provider": "amfi_navall",
      "mode": "ok",
      "message": "14209 AMFI NAV rows parsed; 300 selected"
    },
    "eodBhavcopy": {
      "status": "failed",
      "provider": "none",
      "mode": "failed",
      "message": "nse_bhavcopy bhavcopy unavailable from known candidate URLs; bse_bhavcopy bhavcopy unavailable from known candidate URLs"
    }
  },
  "errors": {}
}
