{
  "categoryCounts": {
    "alerts": 40,
    "shopping": 7
  },
  "contentClassCounts": {
    "upahead_alert": 40,
    "upahead_offer": 7
  },
  "contentHash": "320bdf0831fe",
  "contractVersion": "upahead-lifecycle-v1",
  "errors": [],
  "fetchedAt": 1784628170762,
  "generatedAt": 1784628185139,
  "horizon": {
    "alertFallbackHours": 24,
    "eventPastGraceHours": 24,
    "lookaheadDays": 7,
    "offerFallbackHours": 48,
    "plannerPastGraceHours": 6
  },
  "itemCount": 47,
  "lifecycleSummary": {
    "categoryCounts": {
      "alerts": 40,
      "shopping": 7
    },
    "contentClassCounts": {
      "upahead_alert": 40,
      "upahead_offer": 7
    },
    "horizonViolationCount": 0,
    "horizonViolationSample": [],
    "itemCount": 47,
    "plannerEligibleByLifecycleCount": 47,
    "visibleItemCount": 47
  },
  "plannerEligibleByLifecycleCount": 47,
  "schemaVersion": 1,
  "status": "PASS",
  "thresholds": {
    "eventPastGraceHours": 24,
    "lookaheadDays": 7,
    "minVisibleItems": 3,
    "plannerPastGraceHours": 6
  },
  "visibleItemCount": 47,
  "warnings": []
}